haarcascade/__init__.py
haarcascade/version.py
haar_cascade_nms-1.1.1.dist-info/LICENSE
haar_cascade_nms-1.1.1.dist-info/METADATA
haar_cascade_nms-1.1.1.dist-info/WHEEL
haar_cascade_nms-1.1.1.dist-info/top_level.txt
haar_cascade_nms-1.1.1.dist-info/RECORD
