Metadata-Version: 2.1
Name: haar-cascade-nms
Version: 1.1.1
Summary: Extend opencv haar-cascade detector to filter detections with Non-Maxima Suppression (NMS)
Home-page: https://github.com/LauLauThom/haar-cascade-nms
Author: Laurent Thomas
Author-email: laurent132.thomas@laposte.net
License: UNKNOWN
Keywords: object-recognition object-detection object-localization cascade-detectors haar-cascade opencv
Platform: UNKNOWN
Classifier: Programming Language :: Python :: 3
Classifier: License :: OSI Approved :: MIT License
Classifier: Operating System :: OS Independent
Classifier: Topic :: Scientific/Engineering :: Image Recognition
Classifier: Intended Audience :: Science/Research
License-File: LICENSE
